LICENSE
MANIFEST.in
README.md
pyproject.toml
requirements.txt
setup.py
FastGeodis/__init__.py
FastGeodis/_version.py
FastGeodis/common.h
FastGeodis/fastgeodis.cpp
FastGeodis/fastgeodis.h
FastGeodis/fastgeodis_cpu.cpp
FastGeodis/fastgeodis_cuda.cu
FastGeodis/geodis_fastmarch.cpp
FastGeodis/geodis_pixelqueue.cpp
FastGeodis/geodis_toivanen.cpp
FastGeodis.egg-info/PKG-INFO
FastGeodis.egg-info/SOURCES.txt
FastGeodis.egg-info/dependency_links.txt
FastGeodis.egg-info/not-zip-safe
FastGeodis.egg-info/requires.txt
FastGeodis.egg-info/top_level.txt
dependency/fmm/include/thinks/fast_marching_method/fast_marching_method.hpp