Metadata-Version: 2.1
Name: FastGeodis
Version: 1.0.5
Summary: Fast Implementation of Generalised Geodesic Distance Transform for CPU (OpenMP) and GPU (CUDA)
Home-page: https://github.com/masadcv/FastGeodis
Author: Muhammad Asad
Author-email: masadcv@gmail.com
License: BSD-3-Clause License
Platform: UNKNOWN
Classifier: License :: OSI Approved :: BSD License
Classifier: Programming Language :: Python :: 3
